nettoolkit/__init__.py
nettoolkit/addressing/__init__.py
nettoolkit/addressing/addressing.py
nettoolkit/addressing/batch.py
nettoolkit/addressing/portscan.py
nettoolkit/addressing/subnetscan.py
nettoolkit/addressing/summary.py
nettoolkit/addressing/forms/__init__.py
nettoolkit/addressing/forms/execs.py
nettoolkit/addressing/forms/frames.py
nettoolkit/capture/__init__.py
nettoolkit/capture/commands.py
nettoolkit/capture/device.py
nettoolkit/capture/exceptions.py
nettoolkit/capture/executions.py
nettoolkit/capture/jump_server.py
nettoolkit/capture/validations.py
nettoolkit/capture/forms/__init__.py
nettoolkit/capture/forms/execs.py
nettoolkit/capture/forms/frames.py
nettoolkit/capture_it/__init__.py
nettoolkit/capture_it/_detection.py
nettoolkit/capture_it/cap_summary.py
nettoolkit/capture_it/captures.py
nettoolkit/capture_it/clp.py
nettoolkit/capture_it/command.py
nettoolkit/capture_it/common.py
nettoolkit/capture_it/conn.py
nettoolkit/capture_it/exec_device.py
nettoolkit/capture_it/executions.py
nettoolkit/capture_it/forms/__init__.py
nettoolkit/capture_it/forms/execs.py
nettoolkit/capture_it/forms/frames.py
nettoolkit/compare_it/__init__.py
nettoolkit/compare_it/compare_config.py
nettoolkit/compare_it/diff.py
nettoolkit/compare_it/forms/__init__.py
nettoolkit/compare_it/forms/compare_configs.py
nettoolkit/configure/__init__.py
nettoolkit/configure/configure.py
nettoolkit/configure/forms/__init__.py
nettoolkit/configure/forms/execs.py
nettoolkit/configure/forms/frames.py
nettoolkit/detect/__init__.py
nettoolkit/detect/detection.py
nettoolkit/facts_finder/__init__.py
nettoolkit/facts_finder/clean.py
nettoolkit/facts_finder/exec_fns.py
nettoolkit/facts_finder/inputlog.py
nettoolkit/facts_finder/rearrange.py
nettoolkit/facts_finder/commons/__init__.py
nettoolkit/facts_finder/commons/common.py
nettoolkit/facts_finder/forms/__init__.py
nettoolkit/facts_finder/forms/execs.py
nettoolkit/facts_finder/forms/frames.py
nettoolkit/facts_finder/generators/__init__.py
nettoolkit-1.9.0.dist-info/licenses/LICENSE
nettoolkit-1.9.0.dist-info/METADATA
nettoolkit-1.9.0.dist-info/WHEEL
nettoolkit-1.9.0.dist-info/top_level.txt
nettoolkit-1.9.0.dist-info/RECORD
