Metadata-Version: 2.4
Name: nettoolkit
Version: 1.9.0
Summary: Tool Set for Networking Geeks
Home-page: https://github.com/alias1978/nettoolkit
Author: ALIASGAR - ALI
Author-email: aholo2000@gmail.com
Classifier: Programming Language :: Python :: 3
Classifier: License :: OSI Approved :: MIT License
Classifier: Operating System :: OS Independent
Requires-Python: >=3.10
License-File: LICENSE
Requires-Dist: pandas
Requires-Dist: openpyxl
Requires-Dist: numpy
Requires-Dist: pyfiglet
Requires-Dist: colorama
Requires-Dist: tabulate
Requires-Dist: xlrd
Requires-Dist: jinja2
Requires-Dist: paramiko
Requires-Dist: netmiko
Requires-Dist: ntc-templates
Requires-Dist: pyyaml
Requires-Dist: attrs
Requires-Dist: textfsm
Requires-Dist: jumpssh
Requires-Dist: requests
Dynamic: author
Dynamic: author-email
Dynamic: classifier
Dynamic: description
Dynamic: description-content-type
Dynamic: home-page
Dynamic: license-file
Dynamic: requires-dist
Dynamic: requires-python
Dynamic: summary
